Metadata-Version: 2.1
Name: fourierwavelet
Version: 0.0.6
Summary: Ready-made Fourier transform and Wavelet from a csv file
Home-page: https://github.com/SMALA-comand/Fourier
Author: Artem Radaykin
Author-email: radaykin.artem@mail.ru
License: UNKNOWN
Platform: UNKNOWN
Classifier: Programming Language :: Python :: 3.9
Classifier: License :: OSI Approved :: MIT License
Classifier: Operating System :: OS Independent
